{
  "tech": [
    {
      "title": "USB Cheat Sheet",
      "url": "https://fabiensanglard.net/usbcheat/index.html",
      "score": 120,
      "comments": 39,
      "source": "fabiensanglard.net"
    },
    {
      "title": "The Free Universal Construction Kit",
      "url": "https://fffff.at/free-universal-construction-kit/",
      "score": 256,
      "comments": 47,
      "source": "fffff.at"
    },
    {
      "title": "Trump fires all 24 members of the U.S. National Science Foundation",
      "url": "https://www.science.org/content/article/trump-fires-nsf-s-oversight-board",
      "score": 315,
      "comments": 138,
      "source": "science.org"
    },
    {
      "title": "1-Bit Hokusai's \"The Great Wave\" (2023)",
      "url": "https://www.hypertalking.com/2023/05/08/1-bit-pixel-art-of-hokusais-the-great-wave-off-kanagawa/",
      "score": 515,
      "comments": 86,
      "source": "hypertalking.com"
    },
    {
      "title": "The Joy of Folding Bikes",
      "url": "https://blog.korny.info/2026/04/19/the-joy-of-folding-bikes",
      "score": 68,
      "comments": 38,
      "source": "blog.korny.info"
    },
    {
      "title": "Using coding assistance tools to revive projects you never were going to finish",
      "url": "https://blog.matthewbrunelle.com/its-ok-to-use-coding-assistance-tools-to-revive-the-projects-you-never-were-going-to-finish/",
      "score": 156,
      "comments": 96,
      "source": "blog.matthewbrunelle.com"
    },
    {
      "title": "Why Has There Been So Little Progress on Alzheimer's Disease?",
      "url": "https://freakonomics.com/podcast/why-has-there-been-so-little-progress-on-alzheimers-disease/",
      "score": 7,
      "comments": 0,
      "source": "freakonomics.com"
    },
    {
      "title": "New 10 GbE USB adapters are cooler, smaller, cheaper",
      "url": "https://www.jeffgeerling.com/blog/2026/new-10-gbe-usb-adapters-cooler-smaller-cheaper/",
      "score": 535,
      "comments": 311,
      "source": "jeffgeerling.com"
    },
    {
      "title": "Her Life Savings Mysteriously Disappeared After a Systems Glitch",
      "url": "https://www.nytimes.com/2026/04/25/your-money/fidelity-investments-fraud-alert.html",
      "score": 7,
      "comments": 2,
      "source": "nytimes.com"
    },
    {
      "title": "Simulacrum of Knowledge Work",
      "url": "https://blog.happyfellow.dev/simulacrum-of-knowledge-work/",
      "score": 81,
      "comments": 32,
      "source": "blog.happyfellow.dev"
    }
  ],
  "security": [
    {
      "title": "Protecting your secrets from tomorrow\u2019s quantum risks",
      "url": "https://aws.amazon.com/blogs/security/protecting-your-secrets-from-tomorrows-quantum-risks/",
      "date": "2026-04-24 18:53:29",
      "author": "St\u00e9phanie Mbappe"
    },
    {
      "title": "A technical walkthrough of multicloud full-stack security using AWS Security Hub Extended",
      "url": "https://aws.amazon.com/blogs/security/a-technical-walkthrough-of-multicloud-full-stack-security-using-aws-security-hub-extended/",
      "date": "2026-04-22 16:31:11",
      "author": "Matt Meck"
    },
    {
      "title": "Winter 2025 SOC 1 report is now available with 184 services in scope",
      "url": "https://aws.amazon.com/blogs/security/winter-2025-soc-1-report-is-now-available-with-184-services-in-scope/",
      "date": "2026-04-22 00:12:21",
      "author": "Tushar Jain"
    },
    {
      "title": "How to clone an AWS CloudHSM cluster across Regions",
      "url": "https://aws.amazon.com/blogs/security/how-to-clone-an-aws-cloudhsm-cluster-across-regions-2/",
      "date": "2026-04-20 15:15:47",
      "author": "Desiree Brunner"
    },
    {
      "title": "Transform security logs into OCSF format using a configuration-driven ETL solution",
      "url": "https://aws.amazon.com/blogs/security/transform-security-logs-into-ocsf-format-using-a-configuration-driven-etl-solution/",
      "date": "2026-04-17 16:30:57",
      "author": "Vivek Gautam"
    },
    {
      "title": "Secure AI agent access patterns to AWS resources using Model Context Protocol",
      "url": "https://aws.amazon.com/blogs/security/secure-ai-agent-access-patterns-to-aws-resources-using-model-context-protocol/",
      "date": "2026-04-14 22:52:51",
      "author": "Riggs Goodman III"
    },
    {
      "title": "A framework for securely collecting forensic artifacts into S3 buckets",
      "url": "https://aws.amazon.com/blogs/security/a-framework-for-securely-collecting-forensic-artifacts-into-s3-buckets/",
      "date": "2026-04-08 18:19:00",
      "author": "Jason Garman"
    },
    {
      "title": "Building AI defenses at scale: Before the threats emerge",
      "url": "https://aws.amazon.com/blogs/security/building-ai-defenses-at-scale-before-the-threats-emerge/",
      "date": "2026-04-07 18:02:00",
      "author": "Amy Herzog"
    },
    {
      "title": "Introducing the Landing Zone Accelerator on AWS Universal Configuration and LZA Compliance Workbook",
      "url": "https://aws.amazon.com/blogs/security/introducing-the-landing-zone-accelerator-on-aws-universal-configuration-and-lza-compliance-workbook/",
      "date": "2026-04-04 21:35:00",
      "author": "Kevin Donohue"
    },
    {
      "title": "How AWS KMS and AWS Encryption SDK overcome symmetric encryption bounds",
      "url": "https://aws.amazon.com/blogs/security/how-aws-kms-and-aws-encryption-sdk-overcome-symmetric-encryption-bounds/",
      "date": "2026-04-03 15:44:48",
      "author": "Panos Kampanakis"
    }
  ]
}